{
    "version": "4.5.6",
    "flags": {},
    "shapes": [
        {
            "label": "traffic light",
            "points": [
                [
                    666.6666666666667,
                    1246.099290780142
                ],
                [
                    670.2127659574469,
                    1278.0141843971633
                ],
                [
                    682.2695035460994,
                    1278.0141843971633
                ],
                [
                    680.8510638297872,
                    1246.099290780142
                ]
            ],
            "group_id": null,
            "shape_type": "polygon",
            "flags": {}
        },
        {
            "label": "traffic light",
            "points": [
                [
                    1329.0780141843973,
                    1243.971631205674
                ],
                [
                    1315.6028368794327,
                    1243.2624113475179
                ],
                [
                    1317.0212765957447,
                    1279.4326241134752
                ],
                [
                    1326.9503546099293,
                    1278.0141843971633
                ]
            ],
            "group_id": null,
            "shape_type": "polygon",
            "flags": {}
        },
        {
            "label": "truck",
            "points": [
                [
                    0.08333333333334281,
                    1104.1666666666667
                ],
                [
                    162.58333333333337,
                    1100.0
                ],
                [
                    231.33333333333337,
                    1118.75
                ],
                [
                    241.75,
                    1233.3333333333335
                ],
                [
                    270.9166666666667,
                    1233.3333333333335
                ],
                [
                    481.33333333333337,
                    1233.3333333333335
                ],
                [
                    500.08333333333337,
                    1260.4166666666667
                ],
                [
                    520.9166666666667,
                    1395.8333333333335
                ],
                [
                    485.5,
                    1404.1666666666667
                ],
                [
                    462.58333333333337,
                    1429.1666666666667
                ],
                [
                    391.75,
                    1508.3333333333335
                ],
                [
                    395.91666666666674,
                    1591.6666666666667
                ],
                [
                    368.83333333333337,
                    1625.0
                ],
                [
                    368.83333333333337,
                    1708.3333333333335
                ],
                [
                    325.08333333333337,
                    1712.5
                ],
                [
                    268.83333333333337,
                    1712.5
                ],
                [
                    245.91666666666669,
                    1662.5
                ],
                [
                    220.91666666666669,
                    1637.5
                ],
                [
                    16.75,
                    1645.8333333333335
                ],
                [
                    4.25,
                    1652.0833333333335
                ]
            ],
            "group_id": null,
            "shape_type": "polygon",
            "flags": {}
        },
        {
            "label": "truck",
            "points": [
                [
                    1733.7837837837837,
                    1135.1351351351352
                ],
                [
                    1574.3243243243244,
                    1139.1891891891892
                ],
                [
                    1445.945945945946,
                    1182.4324324324325
                ],
                [
                    1451.3513513513515,
                    1236.4864864864865
                ],
                [
                    1458.1081081081081,
                    1271.6216216216217
                ],
                [
                    1458.1081081081081,
                    1322.972972972973
                ],
                [
                    1447.2972972972973,
                    1352.7027027027027
                ],
                [
                    1456.7567567567569,
                    1368.918918918919
                ],
                [
                    1490.5405405405406,
                    1383.7837837837837
                ],
                [
                    1506.7567567567569,
                    1382.4324324324325
                ],
                [
                    1541.8918918918919,
                    1377.027027027027
                ],
                [
                    1593.2432432432433,
                    1395.945945945946
                ],
                [
                    1597.2972972972973,
                    1448.6486486486488
                ],
                [
                    1636.4864864864865,
                    1437.837837837838
                ],
                [
                    1674.3243243243244,
                    1416.2162162162163
                ],
                [
                    1732.4324324324325,
                    1389.1891891891892
                ]
            ],
            "group_id": null,
            "shape_type": "polygon",
            "flags": {}
        },
        {
            "label": "car",
            "points": [
                [
                    1221.5017064846415,
                    1297.2696245733787
                ],
                [
                    1232.4232081911262,
                    1288.39590443686
                ],
                [
                    1242.6621160409557,
                    1284.641638225256
                ],
                [
                    1260.409556313993,
                    1285.3242320819113
                ],
                [
                    1284.9829351535836,
                    1284.3003412969283
                ],
                [
                    1300.0,
                    1288.0546075085324
                ],
                [
                    1305.8020477815699,
                    1294.8805460750852
                ],
                [
                    1314.334470989761,
                    1317.4061433447098
                ],
                [
                    1312.6279863481227,
                    1335.494880546075
                ],
                [
                    1312.9692832764504,
                    1345.3924914675767
                ],
                [
                    1310.580204778157,
                    1356.655290102389
                ],
                [
                    1295.9044368600682,
                    1356.9965870307167
                ],
                [
                    1293.174061433447,
                    1348.4641638225255
                ],
                [
                    1280.8873720136519,
                    1347.0989761092148
                ],
                [
                    1280.5460750853242,
                    1352.5597269624573
                ],
                [
                    1273.7201365187714,
                    1353.2423208191126
                ],
                [
                    1260.7508532423208,
                    1350.1706484641638
                ],
                [
                    1259.38566552901,
                    1335.8361774744026
                ],
                [
                    1250.1706484641638,
                    1312.286689419795
                ],
                [
                    1242.6621160409557,
                    1303.4129692832764
                ],
                [
                    1231.7406143344708,
                    1300.0
                ]
            ],
            "group_id": null,
            "shape_type": "polygon",
            "flags": {}
        },
        {
            "label": "car",
            "points": [
                [
                    1153.2423208191126,
                    1330.0341296928327
                ],
                [
                    1160.0682593856654,
                    1319.1126279863481
                ],
                [
                    1167.5767918088736,
                    1306.8259385665528
                ],
                [
                    1184.641638225256,
                    1295.9044368600682
                ],
                [
                    1220.8191126279862,
                    1297.952218430034
                ],
                [
                    1238.9078498293516,
                    1301.0238907849828
                ],
                [
                    1248.8054607508532,
                    1309.8976109215016
                ],
                [
                    1253.2423208191126,
                    1323.890784982935
                ],
                [
                    1258.7030716723548,
                    1338.9078498293516
                ],
                [
                    1257.3378839590443,
                    1353.5836177474403
                ],
                [
                    1255.9726962457337,
                    1361.0921501706484
                ],
                [
                    1247.0989761092148,
                    1362.7986348122865
                ],
                [
                    1239.9317406143343,
                    1355.2901023890784
                ],
                [
                    1233.4470989761091,
                    1355.631399317406
                ],
                [
                    1231.0580204778157,
                    1362.4573378839589
                ],
                [
                    1223.890784982935,
                    1362.4573378839589
                ],
                [
                    1218.7713310580205,
                    1355.9726962457337
                ],
                [
                    1198.976109215017,
                    1354.607508532423
                ],
                [
                    1191.4675767918088,
                    1359.38566552901
                ],
                [
                    1190.4436860068258,
                    1364.1638225255972
                ],
                [
                    1158.3617747440273,
                    1362.4573378839589
                ],
                [
                    1155.9726962457337,
                    1349.4880546075085
                ],
                [
                    1149.8293515358362,
                    1344.027303754266
                ],
                [
                    1151.1945392491466,
                    1334.4709897610921
                ]
            ],
            "group_id": null,
            "shape_type": "polygon",
            "flags": {}
        },
        {
            "label": "car",
            "points": [
                [
                    1226.6211604095563,
                    1291.1262798634812
                ],
                [
                    1223.2081911262799,
                    1288.39590443686
                ],
                [
                    1184.3003412969283,
                    1286.0068259385664
                ],
                [
                    1171.3310580204777,
                    1290.4436860068258
                ],
                [
                    1162.7986348122865,
                    1297.952218430034
                ],
                [
                    1158.0204778156997,
                    1305.4607508532422
                ],
                [
                    1148.1228668941978,
                    1305.4607508532422
                ],
                [
                    1142.6621160409557,
                    1312.286689419795
                ],
                [
                    1149.4880546075085,
                    1314.6757679180887
                ],
                [
                    1155.2901023890784,
                    1316.0409556313994
                ],
                [
                    1147.4402730375425,
                    1318.4300341296928
                ],
                [
                    1147.4402730375425,
                    1325.5972696245733
                ],
                [
                    1146.7576791808874,
                    1337.8839590443686
                ],
                [
                    1149.4880546075085,
                    1346.4163822525597
                ],
                [
                    1150.8532423208192,
                    1344.7098976109214
                ],
                [
                    1151.5358361774743,
                    1332.0819112627985
                ],
                [
                    1152.901023890785,
                    1326.2798634812286
                ],
                [
                    1162.7986348122865,
                    1316.0409556313994
                ],
                [
                    1169.283276450512,
                    1304.4368600682594
                ],
                [
                    1185.6655290102387,
                    1297.2696245733787
                ],
                [
                    1220.8191126279862,
                    1298.2935153583617
                ]
            ],
            "group_id": null,
            "shape_type": "polygon",
            "flags": {}
        },
        {
            "label": "car",
            "points": [
                [
                    1161.0921501706484,
                    1300.3412969283277
                ],
                [
                    1131.7406143344708,
                    1300.6825938566553
                ],
                [
                    1125.2559726962456,
                    1307.1672354948805
                ],
                [
                    1121.8430034129692,
                    1319.7952218430034
                ],
                [
                    1122.1843003412969,
                    1345.7337883959044
                ],
                [
                    1150.1706484641638,
                    1348.4641638225255
                ],
                [
                    1147.7815699658702,
                    1338.2252559726962
                ],
                [
                    1148.1228668941978,
                    1317.4061433447098
                ],
                [
                    1155.631399317406,
                    1316.3822525597268
                ],
                [
                    1150.5119453924915,
                    1313.9931740614334
                ],
                [
                    1144.3686006825938,
                    1311.9453924914676
                ],
                [
                    1145.7337883959044,
                    1306.4846416382252
                ],
                [
                    1152.2184300341296,
                    1305.1194539249145
                ],
                [
                    1157.679180887372,
                    1305.4607508532422
                ]
            ],
            "group_id": null,
            "shape_type": "polygon",
            "flags": {}
        },
        {
            "label": "car",
            "points": [
                [
                    1165.2456140350876,
                    1477.1929824561403
                ],
                [
                    1026.6491228070174,
                    1401.7543859649122
                ],
                [
                    903.8421052631578,
                    1370.1754385964912
                ],
                [
                    714.3684210526314,
                    1370.1754385964912
                ],
                [
                    517.8771929824561,
                    1394.736842105263
                ],
                [
                    466.99999999999994,
                    1424.5614035087717
                ],
                [
                    382.78947368421046,
                    1521.0526315789473
                ],
                [
                    384.54385964912274,
                    1596.4912280701753
                ],
                [
                    368.7543859649122,
                    1626.315789473684
                ],
                [
                    372.2631578947368,
                    1705.2631578947367
                ],
                [
                    379.2807017543859,
                    1722.8070175438595
                ],
                [
                    456.47368421052624,
                    1731.5789473684208
                ],
                [
                    466.99999999999994,
                    1659.6491228070174
                ],
                [
                    491.56140350877183,
                    1621.0526315789473
                ],
                [
                    493.31578947368416,
                    1607.0175438596489
                ],
                [
                    574.0175438596491,
                    1582.456140350877
                ],
                [
                    672.2631578947368,
                    1573.6842105263156
                ],
                [
                    777.5263157894736,
                    1529.8245614035086
                ],
                [
                    868.7543859649122,
                    1501.7543859649122
                ],
                [
                    954.7192982456139,
                    1480.7017543859647
                ],
                [
                    1081.0350877192982,
                    1468.4210526315787
                ]
            ],
            "group_id": null,
            "shape_type": "polygon",
            "flags": {}
        },
        {
            "label": "car",
            "points": [
                [
                    1482.7894736842104,
                    1549.1228070175437
                ],
                [
                    1328.4035087719296,
                    1487.7192982456138
                ],
                [
                    1209.1052631578946,
                    1470.1754385964912
                ],
                [
                    1089.8070175438595,
                    1463.1578947368419
                ],
                [
                    972.2631578947368,
                    1478.9473684210525
                ],
                [
                    849.4561403508771,
                    1505.2631578947367
                ],
                [
                    766.9999999999999,
                    1535.0877192982455
                ],
                [
                    666.9999999999999,
                    1575.4385964912278
                ],
                [
                    577.5263157894736,
                    1584.2105263157894
                ],
                [
                    493.31578947368416,
                    1612.2807017543857
                ],
                [
                    482.7894736842105,
                    1638.59649122807
                ],
                [
                    465.24561403508767,
                    1661.4035087719296
                ],
                [
                    451.2105263157894,
                    1728.0701754385964
                ],
                [
                    795.0701754385964,
                    1726.315789473684
                ],
                [
                    795.0701754385964,
                    1740.3508771929824
                ],
                [
                    817.877192982456,
                    1743.8596491228068
                ],
                [
                    824.8947368421052,
                    2015.7894736842104
                ],
                [
                    858.2280701754385,
                    2015.7894736842104
                ],
                [
                    902.0877192982455,
                    1987.7192982456138
                ],
                [
                    924.8947368421052,
                    1959.6491228070174
                ],
                [
                    1216.1228070175437,
                    1952.631578947368
                ],
                [
                    1317.8771929824559,
                    1947.3684210526314
                ],
                [
                    1214.3684210526314,
                    1947.3684210526314
                ],
                [
                    1205.5964912280701,
                    1910.5263157894735
                ],
                [
                    1221.3859649122805,
                    1864.912280701754
                ],
                [
                    1249.4561403508771,
                    1749.1228070175437
                ],
                [
                    1279.2807017543857,
                    1731.5789473684208
                ],
                [
                    1298.5789473684208,
                    1689.4736842105262
                ],
                [
                    1305.5964912280701,
                    1659.6491228070174
                ],
                [
                    1337.1754385964912,
                    1647.3684210526314
                ],
                [
                    1344.1929824561403,
                    1694.736842105263
                ],
                [
                    1388.0526315789473,
                    1710.5263157894735
                ],
                [
                    1416.1228070175437,
                    1703.5087719298244
                ],
                [
                    1658.2280701754385,
                    1729.8245614035086
                ],
                [
                    1674.0175438596489,
                    1952.631578947368
                ],
                [
                    1696.8245614035086,
                    1975.4385964912278
                ],
                [
                    1731.9122807017543,
                    1994.736842105263
                ],
                [
                    1733.6666666666665,
                    1633.3333333333333
                ],
                [
                    1640.6842105263156,
                    1615.7894736842104
                ],
                [
                    1651.2105263157894,
                    1728.0701754385964
                ],
                [
                    1417.8771929824559,
                    1699.9999999999998
                ],
                [
                    1435.4210526315787,
                    1624.5614035087717
                ],
                [
                    1463.4912280701753,
                    1563.1578947368419
                ]
            ],
            "group_id": null,
            "shape_type": "polygon",
            "flags": {}
        },
        {
            "label": "car",
            "points": [
                [
                    1730.1578947368419,
                    1387.7192982456138
                ],
                [
                    1666.9999999999998,
                    1414.0350877192982
                ],
                [
                    1637.175438596491,
                    1435.0877192982455
                ],
                [
                    1586.2982456140348,
                    1447.3684210526314
                ],
                [
                    1603.8421052631577,
                    1473.6842105263156
                ],
                [
                    1619.6315789473683,
                    1535.0877192982455
                ],
                [
                    1637.175438596491,
                    1571.9298245614034
                ],
                [
                    1640.6842105263156,
                    1601.7543859649122
                ],
                [
                    1689.8070175438595,
                    1610.5263157894735
                ],
                [
                    1731.9122807017543,
                    1603.5087719298244
                ]
            ],
            "group_id": null,
            "shape_type": "polygon",
            "flags": {}
        },
        {
            "label": "person",
            "points": [
                [
                    522.3684210526316,
                    1311.1842105263158
                ],
                [
                    525.6578947368421,
                    1292.1052631578948
                ],
                [
                    536.8421052631579,
                    1285.5263157894738
                ],
                [
                    548.6842105263158,
                    1292.1052631578948
                ],
                [
                    550.0,
                    1310.5263157894738
                ],
                [
                    563.8157894736842,
                    1323.0263157894738
                ],
                [
                    569.7368421052631,
                    1347.3684210526317
                ],
                [
                    569.7368421052631,
                    1361.842105263158
                ],
                [
                    569.7368421052631,
                    1388.8157894736842
                ],
                [
                    544.078947368421,
                    1393.421052631579
                ],
                [
                    530.921052631579,
                    1367.7631578947369
                ],
                [
                    523.0263157894736,
                    1334.8684210526317
                ],
                [
                    514.4736842105264,
                    1309.8684210526317
                ]
            ],
            "group_id": null,
            "shape_type": "polygon",
            "flags": {}
        },
        {
            "label": "person",
            "points": [
                [
                    559.2105263157895,
                    1318.421052631579
                ],
                [
                    561.1842105263158,
                    1303.9473684210527
                ],
                [
                    569.078947368421,
                    1300.0
                ],
                [
                    571.7105263157895,
                    1285.5263157894738
                ],
                [
                    580.2631578947369,
                    1285.5263157894738
                ],
                [
                    582.2368421052631,
                    1298.0263157894738
                ],
                [
                    588.1578947368421,
                    1301.9736842105262
                ],
                [
                    590.7894736842105,
                    1321.7105263157894
                ],
                [
                    586.1842105263158,
                    1339.4736842105262
                ],
                [
                    581.578947368421,
                    1370.3947368421052
                ],
                [
                    573.6842105263158,
                    1378.2894736842104
                ],
                [
                    571.7105263157895,
                    1348.0263157894738
                ],
                [
                    564.4736842105264,
                    1328.9473684210527
                ]
            ],
            "group_id": null,
            "shape_type": "polygon",
            "flags": {}
        },
        {
            "label": "person",
            "points": [
                [
                    1619.7547169811319,
                    1533.9622641509434
                ],
                [
                    1600.8867924528302,
                    1464.1509433962262
                ],
                [
                    1591.4528301886792,
                    1415.0943396226414
                ],
                [
                    1559.377358490566,
                    1384.9056603773583
                ],
                [
                    1510.3207547169811,
                    1379.245283018868
                ],
                [
                    1465.0377358490566,
                    1398.1132075471698
                ],
                [
                    1466.9245283018868,
                    1452.830188679245
                ],
                [
                    1449.943396226415,
                    1483.0188679245282
                ],
                [
                    1468.811320754717,
                    1488.6792452830189
                ],
                [
                    1476.3584905660377,
                    1528.3018867924527
                ],
                [
                    1487.6792452830189,
                    1545.2830188679245
                ],
                [
                    1461.264150943396,
                    1575.4716981132074
                ],
                [
                    1429.1886792452829,
                    1652.830188679245
                ],
                [
                    1415.9811320754716,
                    1701.8867924528302
                ],
                [
                    1378.245283018868,
                    1709.4339622641508
                ],
                [
                    1342.3962264150944,
                    1692.4528301886792
                ],
                [
                    1331.0754716981132,
                    1645.2830188679245
                ],
                [
                    1317.8679245283017,
                    1669.811320754717
                ],
                [
                    1300.8867924528302,
                    1688.6792452830189
                ],
                [
                    1304.6603773584905,
                    1709.4339622641508
                ],
                [
                    1344.2830188679245,
                    1741.509433962264
                ],
                [
                    1361.264150943396,
                    1779.245283018868
                ],
                [
                    1393.3396226415093,
                    1773.5849056603772
                ],
                [
                    1404.6603773584905,
                    1779.245283018868
                ],
                [
                    1425.4150943396226,
                    1909.4339622641508
                ],
                [
                    1400.8867924528302,
                    1941.509433962264
                ],
                [
                    1374.4716981132074,
                    1979.245283018868
                ],
                [
                    1359.377358490566,
                    2062.264150943396
                ],
                [
                    1421.6415094339623,
                    2300.0
                ],
                [
                    1419.754716981132,
                    2315.094339622641
                ],
                [
                    1612.2075471698113,
                    2316.9811320754716
                ],
                [
                    1627.3018867924527,
                    2222.6415094339623
                ],
                [
                    1634.8490566037735,
                    2113.2075471698113
                ],
                [
                    1619.7547169811319,
                    2058.490566037736
                ],
                [
                    1619.7547169811319,
                    2011.3207547169811
                ],
                [
                    1651.830188679245,
                    2007.5471698113206
                ],
                [
                    1670.698113207547,
                    2005.6603773584905
                ],
                [
                    1665.0377358490566,
                    1833.9622641509434
                ],
                [
                    1649.943396226415,
                    1720.7547169811319
                ],
                [
                    1644.2830188679245,
                    1584.9056603773583
                ]
            ],
            "group_id": null,
            "shape_type": "polygon",
            "flags": {}
        },
        {
            "label": "handbag",
            "points": [
                [
                    1414.705882352941,
                    1774.9999999999998
                ],
                [
                    1427.941176470588,
                    1845.5882352941176
                ],
                [
                    1427.941176470588,
                    1901.470588235294
                ],
                [
                    1408.8235294117646,
                    1923.5294117647059
                ],
                [
                    1375.0,
                    1924.9999999999998
                ],
                [
                    1311.764705882353,
                    1901.470588235294
                ],
                [
                    1364.705882352941,
                    1779.4117647058822
                ]
            ],
            "group_id": null,
            "shape_type": "polygon",
            "flags": {}
        },
        {
            "label": "handbag",
            "points": [
                [
                    1307.3529411764705,
                    1738.2352941176468
                ],
                [
                    1273.5294117647059,
                    1755.8823529411764
                ],
                [
                    1251.470588235294,
                    1792.6470588235293
                ],
                [
                    1238.235294117647,
                    1855.8823529411764
                ],
                [
                    1242.6470588235293,
                    1886.7647058823527
                ],
                [
                    1294.1176470588234,
                    1899.9999999999998
                ],
                [
                    1345.5882352941176,
                    1811.7647058823527
                ],
                [
                    1332.3529411764705,
                    1766.1764705882351
                ]
            ],
            "group_id": null,
            "shape_type": "polygon",
            "flags": {}
        },
        {
            "label": "handbag",
            "points": [
                [
                    1288.235294117647,
                    1719.1176470588234
                ],
                [
                    1250.0,
                    1747.0588235294117
                ],
                [
                    1239.705882352941,
                    1799.9999999999998
                ],
                [
                    1223.5294117647059,
                    1864.705882352941
                ],
                [
                    1205.8823529411764,
                    1910.2941176470588
                ],
                [
                    1214.705882352941,
                    1948.5294117647059
                ],
                [
                    1320.5882352941176,
                    1948.5294117647059
                ],
                [
                    1320.5882352941176,
                    1914.705882352941
                ],
                [
                    1247.0588235294117,
                    1892.6470588235293
                ],
                [
                    1233.8235294117646,
                    1866.1764705882351
                ],
                [
                    1251.470588235294,
                    1783.8235294117646
                ],
                [
                    1275.0,
                    1755.8823529411764
                ],
                [
                    1307.3529411764705,
                    1733.8235294117646
                ],
                [
                    1332.3529411764705,
                    1723.5294117647059
                ],
                [
                    1313.235294117647,
                    1708.8235294117646
                ]
            ],
            "group_id": null,
            "shape_type": "polygon",
            "flags": {}
        }
    ],
    "imagePath": "../../OlympusEPL6_PNG/OlympusEPL6_0171.PNG",
    "imageData": null,
    "imageHeight": 2320,
    "imageWidth": 1736
}