{
    "version": "4.5.6",
    "flags": {},
    "shapes": [
        {
            "label": "potted plant",
            "points": [
                [
                    170.21052631578948,
                    1508.421052631579
                ],
                [
                    164.9473684210526,
                    1576.842105263158
                ],
                [
                    159.68421052631578,
                    1661.0526315789473
                ],
                [
                    93.89473684210526,
                    1692.6315789473683
                ],
                [
                    1.7894736842105203,
                    1697.8947368421052
                ],
                [
                    4.421052631578931,
                    1140.0
                ],
                [
                    75.4736842105263,
                    1155.7894736842104
                ],
                [
                    128.10526315789474,
                    1208.421052631579
                ],
                [
                    112.31578947368422,
                    1447.8947368421052
                ],
                [
                    104.42105263157896,
                    1476.842105263158
                ]
            ],
            "group_id": null,
            "shape_type": "polygon",
            "flags": {}
        },
        {
            "label": "potted plant",
            "points": [
                [
                    93.89473684210526,
                    1387.3684210526317
                ],
                [
                    112.31578947368422,
                    1476.842105263158
                ],
                [
                    180.73684210526318,
                    1511.0526315789473
                ],
                [
                    183.36842105263156,
                    1179.4736842105262
                ],
                [
                    128.10526315789474,
                    1084.7368421052631
                ],
                [
                    57.05263157894734,
                    1045.2631578947369
                ],
                [
                    12.31578947368422,
                    1055.7894736842104
                ],
                [
                    38.63157894736841,
                    1140.0
                ],
                [
                    117.57894736842104,
                    1224.2105263157894
                ],
                [
                    122.84210526315792,
                    1358.421052631579
                ]
            ],
            "group_id": null,
            "shape_type": "polygon",
            "flags": {}
        },
        {
            "label": "parking meter",
            "points": [
                [
                    394.6666666666667,
                    888.0
                ],
                [
                    434.6666666666667,
                    889.3333333333334
                ],
                [
                    436.0,
                    942.6666666666666
                ],
                [
                    428.0,
                    945.3333333333334
                ],
                [
                    425.3333333333333,
                    1001.3333333333334
                ],
                [
                    394.6666666666667,
                    1005.3333333333334
                ]
            ],
            "group_id": null,
            "shape_type": "polygon",
            "flags": {}
        },
        {
            "label": "backpack",
            "points": [
                [
                    538.6666666666666,
                    873.3333333333334
                ],
                [
                    561.3333333333334,
                    861.3333333333334
                ],
                [
                    584.0,
                    873.3333333333334
                ],
                [
                    584.0,
                    909.3333333333334
                ],
                [
                    577.3333333333334,
                    976.0
                ],
                [
                    569.3333333333334,
                    986.6666666666666
                ],
                [
                    541.3333333333334,
                    982.6666666666666
                ],
                [
                    509.3333333333333,
                    958.6666666666666
                ],
                [
                    520.0,
                    936.0
                ]
            ],
            "group_id": null,
            "shape_type": "polygon",
            "flags": {}
        },
        {
            "label": "person",
            "points": [
                [
                    581.3333333333334,
                    790.6666666666666
                ],
                [
                    566.6666666666666,
                    792.0
                ],
                [
                    556.0,
                    798.6666666666666
                ],
                [
                    560.0,
                    841.3333333333334
                ],
                [
                    536.0,
                    846.6666666666666
                ],
                [
                    514.6666666666666,
                    910.6666666666666
                ],
                [
                    521.3333333333334,
                    926.6666666666666
                ],
                [
                    508.0,
                    957.3333333333334
                ],
                [
                    537.3333333333334,
                    985.3333333333334
                ],
                [
                    529.3333333333334,
                    1033.3333333333333
                ],
                [
                    545.3333333333334,
                    1100.0
                ],
                [
                    557.3333333333334,
                    1113.3333333333333
                ],
                [
                    576.0,
                    1117.3333333333333
                ],
                [
                    589.3333333333334,
                    1088.0
                ],
                [
                    614.6666666666666,
                    974.6666666666666
                ],
                [
                    613.3333333333334,
                    902.6666666666666
                ],
                [
                    625.3333333333334,
                    985.3333333333334
                ],
                [
                    633.3333333333334,
                    1010.6666666666666
                ],
                [
                    642.6666666666666,
                    1006.6666666666666
                ],
                [
                    646.6666666666666,
                    978.6666666666666
                ],
                [
                    626.6666666666666,
                    894.6666666666666
                ],
                [
                    608.0,
                    846.6666666666666
                ],
                [
                    598.6666666666666,
                    846.6666666666666
                ],
                [
                    604.0,
                    822.6666666666666
                ],
                [
                    604.0,
                    796.0
                ]
            ],
            "group_id": null,
            "shape_type": "polygon",
            "flags": {}
        },
        {
            "label": "person",
            "points": [
                [
                    942.6666666666666,
                    860.0
                ],
                [
                    926.6666666666666,
                    860.0
                ],
                [
                    926.6666666666666,
                    880.0
                ],
                [
                    918.6666666666666,
                    889.3333333333334
                ],
                [
                    896.0,
                    952.0
                ],
                [
                    909.3333333333334,
                    964.0
                ],
                [
                    916.0,
                    1028.0
                ],
                [
                    942.6666666666666,
                    1030.6666666666667
                ],
                [
                    956.0,
                    958.6666666666666
                ],
                [
                    961.3333333333334,
                    948.0
                ],
                [
                    956.0,
                    897.3333333333334
                ],
                [
                    946.6666666666666,
                    884.0
                ]
            ],
            "group_id": null,
            "shape_type": "polygon",
            "flags": {}
        },
        {
            "label": "person",
            "points": [
                [
                    2002.469135802469,
                    877.3662551440328
                ],
                [
                    1999.1769547325102,
                    860.9053497942386
                ],
                [
                    1996.707818930041,
                    853.0864197530864
                ],
                [
                    1987.6543209876543,
                    851.8518518518518
                ],
                [
                    1986.8312757201645,
                    858.4362139917695
                ],
                [
                    1982.716049382716,
                    862.1399176954732
                ],
                [
                    1981.0699588477364,
                    876.1316872427983
                ],
                [
                    1985.185185185185,
                    881.4814814814814
                ],
                [
                    1998.3539094650205,
                    882.3045267489712
                ]
            ],
            "group_id": null,
            "shape_type": "polygon",
            "flags": {}
        },
        {
            "label": "potted plant",
            "points": [
                [
                    1100.0,
                    914.8148148148148
                ],
                [
                    1092.1810699588477,
                    930.4526748971193
                ],
                [
                    1094.238683127572,
                    951.440329218107
                ],
                [
                    1107.8189300411523,
                    963.3744855967077
                ],
                [
                    1133.7448559670781,
                    964.6090534979423
                ],
                [
                    1134.9794238683128,
                    959.670781893004
                ],
                [
                    1131.275720164609,
                    947.3251028806584
                ],
                [
                    1130.8641975308642,
                    929.6296296296296
                ],
                [
                    1138.2716049382716,
                    918.1069958847736
                ],
                [
                    1125.514403292181,
                    909.8765432098764
                ],
                [
                    1111.522633744856,
                    899.9999999999999
                ],
                [
                    1111.522633744856,
                    889.3004115226337
                ],
                [
                    1128.395061728395,
                    872.8395061728395
                ],
                [
                    1138.2716049382716,
                    866.6666666666666
                ],
                [
                    1105.349794238683,
                    870.7818930041152
                ],
                [
                    1097.5308641975307,
                    874.8971193415638
                ],
                [
                    1086.4197530864196,
                    881.8930041152263
                ],
                [
                    1078.6008230452674,
                    894.2386831275719
                ],
                [
                    1083.1275720164608,
                    907.4074074074074
                ]
            ],
            "group_id": null,
            "shape_type": "polygon",
            "flags": {}
        },
        {
            "label": "potted plant",
            "points": [
                [
                    1137.4485596707818,
                    918.1069958847736
                ],
                [
                    1130.4526748971193,
                    927.9835390946502
                ],
                [
                    1130.4526748971193,
                    951.0288065843621
                ],
                [
                    1140.7407407407406,
                    964.6090534979423
                ],
                [
                    1149.3827160493827,
                    970.7818930041152
                ],
                [
                    1171.6049382716049,
                    971.6049382716049
                ],
                [
                    1188.0658436213992,
                    956.7901234567901
                ],
                [
                    1191.358024691358,
                    941.5637860082304
                ],
                [
                    1185.1851851851852,
                    921.3991769547324
                ],
                [
                    1198.3539094650205,
                    917.6954732510287
                ],
                [
                    1208.2304526748972,
                    907.4074074074074
                ],
                [
                    1208.2304526748972,
                    888.0658436213992
                ],
                [
                    1203.2921810699588,
                    880.6584362139918
                ],
                [
                    1185.5967078189299,
                    872.0164609053497
                ],
                [
                    1174.8971193415637,
                    864.6090534979423
                ],
                [
                    1158.0246913580247,
                    865.0205761316872
                ],
                [
                    1135.8024691358023,
                    867.4897119341563
                ],
                [
                    1123.4567901234568,
                    876.1316872427983
                ],
                [
                    1113.5802469135801,
                    891.358024691358
                ],
                [
                    1116.460905349794,
                    905.7613168724279
                ],
                [
                    1122.633744855967,
                    912.7572016460905
                ]
            ],
            "group_id": null,
            "shape_type": "polygon",
            "flags": {}
        },
        {
            "label": "potted plant",
            "points": [
                [
                    1263.3744855967077,
                    910.6995884773662
                ],
                [
                    1255.5555555555554,
                    918.9300411522634
                ],
                [
                    1254.320987654321,
                    929.2181069958847
                ],
                [
                    1253.9094650205761,
                    939.0946502057612
                ],
                [
                    1260.4938271604938,
                    949.7942386831276
                ],
                [
                    1274.8971193415637,
                    956.3786008230452
                ],
                [
                    1285.5967078189299,
                    956.7901234567901
                ],
                [
                    1302.469135802469,
                    945.679012345679
                ],
                [
                    1303.2921810699588,
                    932.5102880658436
                ],
                [
                    1302.469135802469,
                    920.5761316872428
                ],
                [
                    1295.0617283950617,
                    911.9341563786007
                ],
                [
                    1307.8189300411523,
                    906.5843621399176
                ],
                [
                    1318.1069958847736,
                    897.9423868312757
                ],
                [
                    1324.6913580246912,
                    890.1234567901234
                ],
                [
                    1323.4567901234568,
                    880.2469135802469
                ],
                [
                    1314.40329218107,
                    873.2510288065843
                ],
                [
                    1298.7654320987654,
                    873.6625514403291
                ],
                [
                    1289.7119341563784,
                    870.3703703703703
                ],
                [
                    1277.366255144033,
                    867.9012345679012
                ],
                [
                    1268.312757201646,
                    870.7818930041152
                ],
                [
                    1256.79012345679,
                    874.8971193415638
                ],
                [
                    1248.9711934156378,
                    884.7736625514402
                ],
                [
                    1253.4979423868313,
                    893.0041152263374
                ],
                [
                    1258.0246913580247,
                    906.1728395061727
                ]
            ],
            "group_id": null,
            "shape_type": "polygon",
            "flags": {}
        },
        {
            "label": "potted plant",
            "points": [
                [
                    1423.8683127572015,
                    911.5226337448559
                ],
                [
                    1416.872427983539,
                    905.7613168724279
                ],
                [
                    1409.4650205761316,
                    908.6419753086419
                ],
                [
                    1406.9958847736625,
                    914.8148148148148
                ],
                [
                    1413.5802469135801,
                    924.6913580246913
                ],
                [
                    1413.991769547325,
                    936.6255144032921
                ],
                [
                    1407.8189300411523,
                    948.148148148148
                ],
                [
                    1387.2427983539094,
                    950.6172839506172
                ],
                [
                    1371.19341563786,
                    937.037037037037
                ],
                [
                    1369.1358024691358,
                    920.9876543209876
                ],
                [
                    1378.6008230452674,
                    912.7572016460905
                ],
                [
                    1383.1275720164608,
                    909.4650205761317
                ],
                [
                    1383.5390946502057,
                    895.4732510288065
                ],
                [
                    1371.6049382716049,
                    888.8888888888888
                ],
                [
                    1373.662551440329,
                    879.4238683127571
                ],
                [
                    1383.9506172839506,
                    872.0164609053497
                ],
                [
                    1400.4115226337447,
                    869.5473251028806
                ],
                [
                    1409.8765432098764,
                    872.4279835390946
                ],
                [
                    1416.872427983539,
                    877.7777777777777
                ],
                [
                    1423.4567901234566,
                    883.9506172839506
                ],
                [
                    1427.1604938271605,
                    894.6502057613168
                ],
                [
                    1428.8065843621398,
                    907.4074074074074
                ]
            ],
            "group_id": null,
            "shape_type": "polygon",
            "flags": {}
        },
        {
            "label": "potted plant",
            "points": [
                [
                    1370.781893004115,
                    939.0946502057612
                ],
                [
                    1362.139917695473,
                    937.8600823045267
                ],
                [
                    1353.4979423868313,
                    930.0411522633744
                ],
                [
                    1350.617283950617,
                    917.6954732510287
                ],
                [
                    1352.6748971193415,
                    913.1687242798354
                ],
                [
                    1346.9135802469134,
                    901.2345679012345
                ],
                [
                    1342.3868312757202,
                    887.2427983539094
                ],
                [
                    1347.3251028806583,
                    882.7160493827159
                ],
                [
                    1362.9629629629628,
                    877.7777777777777
                ],
                [
                    1373.2510288065844,
                    880.2469135802469
                ],
                [
                    1372.4279835390946,
                    907.4074074074074
                ],
                [
                    1371.19341563786,
                    932.5102880658436
                ]
            ],
            "group_id": null,
            "shape_type": "polygon",
            "flags": {}
        },
        {
            "label": "potted plant",
            "points": [
                [
                    1490.1234567901233,
                    923.0452674897118
                ],
                [
                    1492.1810699588477,
                    940.3292181069958
                ],
                [
                    1502.880658436214,
                    938.6831275720164
                ],
                [
                    1505.349794238683,
                    924.2798353909465
                ],
                [
                    1506.5843621399176,
                    906.5843621399176
                ],
                [
                    1495.8847736625514,
                    905.7613168724279
                ],
                [
                    1494.238683127572,
                    921.8106995884773
                ]
            ],
            "group_id": null,
            "shape_type": "polygon",
            "flags": {}
        },
        {
            "label": "potted plant",
            "points": [
                [
                    1505.349794238683,
                    923.0452674897118
                ],
                [
                    1507.8189300411523,
                    939.917695473251
                ],
                [
                    1515.6378600823043,
                    938.6831275720164
                ],
                [
                    1521.8106995884773,
                    926.3374485596707
                ],
                [
                    1518.5185185185185,
                    906.5843621399176
                ],
                [
                    1507.8189300411523,
                    905.7613168724279
                ],
                [
                    1509.4650205761316,
                    920.5761316872428
                ]
            ],
            "group_id": null,
            "shape_type": "polygon",
            "flags": {}
        },
        {
            "label": "potted plant",
            "points": [
                [
                    1532.0987654320986,
                    912.3456790123456
                ],
                [
                    1524.2798353909463,
                    922.2222222222222
                ],
                [
                    1524.2798353909463,
                    931.6872427983539
                ],
                [
                    1529.6296296296296,
                    944.0329218106996
                ],
                [
                    1541.5637860082304,
                    948.9711934156378
                ],
                [
                    1547.7366255144032,
                    915.6378600823044
                ],
                [
                    1555.1440329218105,
                    946.0905349794238
                ],
                [
                    1559.670781893004,
                    930.8641975308641
                ],
                [
                    1565.8436213991768,
                    928.8065843621398
                ],
                [
                    1565.0205761316872,
                    920.9876543209876
                ],
                [
                    1559.2592592592591,
                    910.2880658436213
                ],
                [
                    1576.1316872427983,
                    907.4074074074074
                ],
                [
                    1586.0082304526748,
                    902.0576131687242
                ],
                [
                    1586.8312757201645,
                    889.3004115226337
                ],
                [
                    1579.4238683127571,
                    883.5390946502057
                ],
                [
                    1566.6666666666665,
                    877.3662551440328
                ],
                [
                    1558.8477366255142,
                    874.074074074074
                ],
                [
                    1546.0905349794239,
                    873.6625514403291
                ],
                [
                    1540.3292181069958,
                    877.3662551440328
                ],
                [
                    1527.98353909465,
                    881.0699588477365
                ],
                [
                    1523.4567901234566,
                    884.7736625514402
                ],
                [
                    1514.8148148148148,
                    890.5349794238682
                ],
                [
                    1512.7572016460904,
                    893.0041152263374
                ],
                [
                    1512.7572016460904,
                    902.469135802469
                ],
                [
                    1521.8106995884773,
                    909.0534979423868
                ]
            ],
            "group_id": null,
            "shape_type": "polygon",
            "flags": {}
        },
        {
            "label": "car",
            "points": [
                [
                    2094.366197183099,
                    888.7323943661972
                ],
                [
                    2035.9154929577467,
                    885.2112676056338
                ],
                [
                    2025.3521126760565,
                    890.8450704225353
                ],
                [
                    2049.2957746478874,
                    917.6056338028169
                ],
                [
                    2057.042253521127,
                    927.4647887323944
                ],
                [
                    2085.211267605634,
                    933.8028169014085
                ],
                [
                    2094.366197183099,
                    933.8028169014085
                ]
            ],
            "group_id": null,
            "shape_type": "polygon",
            "flags": {}
        },
        {
            "label": "car",
            "points": [
                [
                    2062.676056338028,
                    936.6197183098592
                ],
                [
                    2047.887323943662,
                    911.9718309859155
                ],
                [
                    2026.7605633802818,
                    888.7323943661972
                ],
                [
                    2003.5211267605634,
                    887.3239436619718
                ],
                [
                    1926.7605633802818,
                    878.8732394366198
                ],
                [
                    1898.5915492957747,
                    888.7323943661972
                ],
                [
                    1869.0140845070423,
                    907.0422535211268
                ],
                [
                    1888.7323943661972,
                    932.3943661971831
                ],
                [
                    1890.1408450704225,
                    927.4647887323944
                ],
                [
                    1907.7464788732395,
                    930.9859154929578
                ],
                [
                    1909.8591549295775,
                    942.9577464788733
                ],
                [
                    1897.1830985915494,
                    944.3661971830986
                ],
                [
                    1897.887323943662,
                    948.5915492957747
                ],
                [
                    1929.5774647887324,
                    961.2676056338029
                ],
                [
                    1938.0281690140846,
                    977.4647887323944
                ],
                [
                    1938.7323943661972,
                    1000.0
                ],
                [
                    1961.9718309859156,
                    1003.5211267605634
                ],
                [
                    1990.1408450704225,
                    1008.4507042253522
                ],
                [
                    2009.1549295774648,
                    1023.2394366197184
                ],
                [
                    2020.4225352112678,
                    1020.4225352112677
                ],
                [
                    1996.4788732394368,
                    997.8873239436621
                ],
                [
                    2014.0845070422536,
                    979.5774647887324
                ],
                [
                    2026.0563380281692,
                    966.9014084507043
                ],
                [
                    2063.380281690141,
                    952.112676056338
                ]
            ],
            "group_id": null,
            "shape_type": "polygon",
            "flags": {}
        },
        {
            "label": "car",
            "points": [
                [
                    1930.708661417323,
                    960.6299212598425
                ],
                [
                    1896.0629921259842,
                    949.6062992125984
                ],
                [
                    1908.6614173228347,
                    941.7322834645669
                ],
                [
                    1907.8740157480315,
                    929.9212598425197
                ],
                [
                    1886.6141732283463,
                    929.9212598425197
                ],
                [
                    1869.291338582677,
                    906.2992125984251
                ],
                [
                    1855.9055118110236,
                    878.7401574803149
                ],
                [
                    1814.9606299212599,
                    872.4409448818898
                ],
                [
                    1803.1496062992126,
                    870.0787401574803
                ],
                [
                    1789.763779527559,
                    855.9055118110236
                ],
                [
                    1770.8661417322835,
                    857.4803149606299
                ],
                [
                    1761.4173228346456,
                    868.503937007874
                ],
                [
                    1692.9133858267717,
                    868.503937007874
                ],
                [
                    1666.1417322834645,
                    870.0787401574803
                ],
                [
                    1646.4566929133857,
                    870.0787401574803
                ],
                [
                    1603.1496062992126,
                    924.4094488188977
                ],
                [
                    1558.267716535433,
                    929.9212598425197
                ],
                [
                    1550.3937007874015,
                    974.0157480314961
                ],
                [
                    1547.244094488189,
                    978.7401574803149
                ],
                [
                    1544.8818897637796,
                    988.1889763779527
                ],
                [
                    1551.9685039370079,
                    1014.9606299212599
                ],
                [
                    1565.3543307086613,
                    1026.7716535433071
                ],
                [
                    1586.6141732283465,
                    1029.9212598425197
                ],
                [
                    1592.9133858267717,
                    1049.6062992125985
                ],
                [
                    1600.7874015748032,
                    1062.2047244094488
                ],
                [
                    1630.708661417323,
                    1062.992125984252
                ],
                [
                    1634.6456692913387,
                    1048.0314960629921
                ],
                [
                    1641.732283464567,
                    1040.9448818897638
                ],
                [
                    1655.9055118110236,
                    1037.007874015748
                ],
                [
                    1694.4881889763778,
                    1039.3700787401574
                ],
                [
                    1722.0472440944882,
                    1040.9448818897638
                ],
                [
                    1762.992125984252,
                    1048.0314960629921
                ],
                [
                    1771.6535433070867,
                    1057.4803149606298
                ],
                [
                    1776.3779527559054,
                    1070.8661417322835
                ],
                [
                    1799.2125984251968,
                    1069.291338582677
                ],
                [
                    1817.3228346456692,
                    1054.3307086614172
                ],
                [
                    1886.6141732283463,
                    1039.3700787401574
                ],
                [
                    1892.1259842519685,
                    1049.6062992125985
                ],
                [
                    1901.5748031496062,
                    1052.755905511811
                ],
                [
                    1922.0472440944882,
                    1051.9685039370079
                ],
                [
                    1933.0708661417323,
                    1035.4330708661416
                ],
                [
                    1938.5826771653542,
                    1007.0866141732283
                ],
                [
                    1940.1574803149606,
                    981.1023622047244
                ]
            ],
            "group_id": null,
            "shape_type": "polygon",
            "flags": {}
        },
        {
            "label": "car",
            "points": [
                [
                    1095.483870967742,
                    863.2258064516129
                ],
                [
                    1085.8064516129032,
                    861.2903225806451
                ],
                [
                    1085.1612903225807,
                    841.2903225806451
                ],
                [
                    1049.6774193548388,
                    842.5806451612902
                ],
                [
                    1049.6774193548388,
                    862.5806451612902
                ],
                [
                    1014.8387096774193,
                    867.741935483871
                ],
                [
                    1000.6451612903226,
                    889.6774193548387
                ],
                [
                    976.1290322580645,
                    890.9677419354839
                ],
                [
                    969.6774193548387,
                    913.5483870967741
                ],
                [
                    979.3548387096774,
                    931.6129032258065
                ],
                [
                    990.3225806451612,
                    938.0645161290322
                ],
                [
                    993.5483870967741,
                    948.3870967741935
                ],
                [
                    1016.7741935483871,
                    949.6774193548387
                ],
                [
                    1018.0645161290322,
                    941.2903225806451
                ],
                [
                    1057.4193548387098,
                    943.2258064516129
                ],
                [
                    1066.4516129032259,
                    952.258064516129
                ],
                [
                    1082.5806451612902,
                    954.8387096774193
                ],
                [
                    1084.516129032258,
                    953.5483870967741
                ],
                [
                    1083.8709677419354,
                    907.0967741935484
                ],
                [
                    1078.0645161290322,
                    893.5483870967741
                ],
                [
                    1083.225806451613,
                    880.0
                ],
                [
                    1097.4193548387098,
                    874.1935483870967
                ]
            ],
            "group_id": null,
            "shape_type": "polygon",
            "flags": {}
        },
        {
            "label": "potted plant",
            "points": [
                [
                    705.3691275167786,
                    924.8322147651007
                ],
                [
                    697.3154362416108,
                    932.8859060402684
                ],
                [
                    692.6174496644295,
                    944.2953020134228
                ],
                [
                    689.261744966443,
                    960.4026845637584
                ],
                [
                    697.9865771812081,
                    981.2080536912752
                ],
                [
                    713.4228187919463,
                    988.5906040268457
                ],
                [
                    738.9261744966443,
                    988.5906040268457
                ],
                [
                    750.3355704697987,
                    984.5637583892618
                ],
                [
                    758.3892617449665,
                    969.1275167785235
                ],
                [
                    763.7583892617449,
                    942.9530201342282
                ],
                [
                    757.0469798657718,
                    930.8724832214765
                ],
                [
                    771.1409395973154,
                    918.1208053691275
                ],
                [
                    787.9194630872483,
                    912.751677852349
                ],
                [
                    790.6040268456376,
                    891.2751677852349
                ],
                [
                    775.1677852348994,
                    874.496644295302
                ],
                [
                    753.0201342281879,
                    866.4429530201343
                ],
                [
                    722.8187919463087,
                    859.7315436241611
                ],
                [
                    689.261744966443,
                    869.7986577181208
                ],
                [
                    673.8255033557047,
                    879.8657718120805
                ],
                [
                    668.4563758389262,
                    890.6040268456376
                ],
                [
                    664.4295302013422,
                    904.6979865771813
                ],
                [
                    675.8389261744967,
                    918.7919463087248
                ]
            ],
            "group_id": null,
            "shape_type": "polygon",
            "flags": {}
        },
        {
            "label": "potted plant",
            "points": [
                [
                    666.4429530201343,
                    922.8187919463087
                ],
                [
                    661.744966442953,
                    936.2416107382551
                ],
                [
                    662.4161073825503,
                    948.993288590604
                ],
                [
                    668.4563758389262,
                    959.0604026845638
                ],
                [
                    678.5234899328859,
                    974.4966442953021
                ],
                [
                    699.3288590604027,
                    981.8791946308725
                ],
                [
                    689.261744966443,
                    958.3892617449665
                ],
                [
                    689.261744966443,
                    946.3087248322148
                ],
                [
                    695.9731543624162,
                    935.5704697986578
                ],
                [
                    704.6979865771813,
                    925.503355704698
                ],
                [
                    673.1543624161073,
                    919.4630872483222
                ],
                [
                    663.7583892617449,
                    900.0
                ],
                [
                    675.8389261744967,
                    881.2080536912752
                ],
                [
                    694.6308724832214,
                    871.8120805369127
                ],
                [
                    708.0536912751678,
                    863.0872483221476
                ],
                [
                    691.2751677852349,
                    863.7583892617449
                ],
                [
                    668.4563758389262,
                    869.7986577181208
                ],
                [
                    648.3221476510067,
                    883.2214765100671
                ],
                [
                    643.6241610738255,
                    889.9328859060403
                ],
                [
                    640.2684563758389,
                    902.0134228187919
                ],
                [
                    648.3221476510067,
                    916.1073825503356
                ]
            ],
            "group_id": null,
            "shape_type": "polygon",
            "flags": {}
        },
        {
            "label": "fire hydrant",
            "points": [
                [
                    422.8888888888889,
                    1671.5555555555557
                ],
                [
                    372.8888888888889,
                    1671.5555555555557
                ],
                [
                    336.7777777777778,
                    1666.0
                ],
                [
                    334.0,
                    1629.888888888889
                ],
                [
                    347.8888888888889,
                    1621.5555555555557
                ],
                [
                    436.7777777777778,
                    1621.5555555555557
                ],
                [
                    453.44444444444446,
                    1663.2222222222224
                ]
            ],
            "group_id": null,
            "shape_type": "polygon",
            "flags": {}
        }
    ],
    "imagePath": "../../OlympusEPL6_PNG/OlympusEPL6_0170.PNG",
    "imageData": null,
    "imageHeight": 1736,
    "imageWidth": 2320
}