{
    "version": "4.5.6",
    "flags": {},
    "shapes": [
        {
            "label": "chair",
            "points": [
                [
                    1508.5263157894735,
                    1144.9122807017543
                ],
                [
                    1499.7543859649122,
                    1123.8596491228068
                ],
                [
                    1483.9649122807016,
                    1111.5789473684208
                ],
                [
                    1478.7017543859647,
                    939.6491228070174
                ],
                [
                    1531.3333333333333,
                    651.9298245614034
                ],
                [
                    1494.4912280701753,
                    651.9298245614034
                ],
                [
                    1483.9649122807016,
                    720.3508771929824
                ],
                [
                    1403.2631578947367,
                    679.9999999999999
                ],
                [
                    1415.5438596491226,
                    601.0526315789473
                ],
                [
                    1373.4385964912278,
                    606.3157894736842
                ],
                [
                    1361.1578947368419,
                    651.9298245614034
                ],
                [
                    1199.7543859649122,
                    671.2280701754385
                ],
                [
                    1192.7368421052631,
                    616.8421052631578
                ],
                [
                    1166.4210526315787,
                    632.6315789473683
                ],
                [
                    1180.4561403508771,
                    808.0701754385964
                ],
                [
                    1247.1228070175437,
                    879.9999999999999
                ],
                [
                    1275.1929824561403,
                    974.7368421052631
                ],
                [
                    1457.6491228070174,
                    927.3684210526314
                ],
                [
                    1338.3508771929824,
                    960.7017543859647
                ],
                [
                    1352.3859649122805,
                    1034.3859649122805
                ],
                [
                    1464.6666666666665,
                    1134.3859649122805
                ]
            ],
            "group_id": null,
            "shape_type": "polygon",
            "flags": {}
        },
        {
            "label": "chair",
            "points": [
                [
                    962.9122807017543,
                    495.7894736842104
                ],
                [
                    950.6315789473683,
                    501.0526315789473
                ],
                [
                    971.6842105263157,
                    608.0701754385964
                ],
                [
                    1034.8421052631577,
                    636.1403508771929
                ],
                [
                    1115.5438596491226,
                    678.2456140350877
                ],
                [
                    1194.4912280701753,
                    657.1929824561403
                ],
                [
                    1206.7719298245613,
                    511.5789473684209
                ],
                [
                    1176.9473684210525,
                    548.4210526315788
                ],
                [
                    1168.1754385964912,
                    594.0350877192982
                ],
                [
                    1138.3508771929824,
                    579.9999999999999
                ],
                [
                    1148.877192982456,
                    474.7368421052631
                ],
                [
                    1129.578947368421,
                    474.7368421052631
                ],
                [
                    1113.7894736842104,
                    532.6315789473683
                ],
                [
                    983.9649122807017,
                    550.1754385964912
                ]
            ],
            "group_id": null,
            "shape_type": "polygon",
            "flags": {}
        },
        {
            "label": "chair",
            "points": [
                [
                    1278.7017543859647,
                    537.8947368421052
                ],
                [
                    1255.8947368421052,
                    544.9122807017543
                ],
                [
                    1250.6315789473683,
                    585.2631578947368
                ],
                [
                    1101.5087719298244,
                    581.7543859649122
                ],
                [
                    1099.7543859649122,
                    546.6666666666666
                ],
                [
                    1076.9473684210525,
                    537.8947368421052
                ],
                [
                    1075.1929824561403,
                    641.4035087719298
                ],
                [
                    1171.6842105263156,
                    706.3157894736842
                ],
                [
                    1254.1403508771928,
                    741.4035087719298
                ],
                [
                    1268.1754385964912,
                    832.6315789473683
                ],
                [
                    1331.3333333333333,
                    818.59649122807
                ],
                [
                    1371.6842105263156,
                    579.9999999999999
                ],
                [
                    1352.3859649122805,
                    579.9999999999999
                ],
                [
                    1331.3333333333333,
                    636.1403508771929
                ],
                [
                    1275.1929824561403,
                    613.3333333333333
                ]
            ],
            "group_id": null,
            "shape_type": "polygon",
            "flags": {}
        },
        {
            "label": "chair",
            "points": [
                [
                    661.1578947368421,
                    544.9122807017543
                ],
                [
                    683.9649122807017,
                    681.7543859649122
                ],
                [
                    729.5789473684209,
                    723.8596491228069
                ],
                [
                    936.59649122807,
                    723.8596491228069
                ],
                [
                    933.0877192982455,
                    567.7192982456139
                ],
                [
                    913.7894736842104,
                    562.4561403508771
                ],
                [
                    906.7719298245613,
                    618.5964912280701
                ],
                [
                    878.7017543859648,
                    588.7719298245613
                ],
                [
                    889.2280701754385,
                    523.8596491228069
                ],
                [
                    857.6491228070174,
                    530.8771929824561
                ],
                [
                    855.8947368421052,
                    569.4736842105262
                ],
                [
                    692.7368421052631,
                    583.5087719298244
                ],
                [
                    676.9473684210526,
                    530.8771929824561
                ]
            ],
            "group_id": null,
            "shape_type": "polygon",
            "flags": {}
        },
        {
            "label": "chair",
            "points": [
                [
                    934.8421052631578,
                    1355.4385964912278
                ],
                [
                    1175.1929824561403,
                    1257.1929824561403
                ],
                [
                    1122.5614035087717,
                    1397.5438596491226
                ],
                [
                    1193.0,
                    1459.0
                ],
                [
                    1233.0877192982455,
                    1453.6842105263156
                ],
                [
                    1224.3157894736842,
                    1439.6491228070174
                ],
                [
                    1215.5438596491226,
                    1413.3333333333333
                ],
                [
                    1205.017543859649,
                    1211.5789473684208
                ],
                [
                    1224.3157894736842,
                    892.2807017543859
                ],
                [
                    1208.5263157894735,
                    881.7543859649122
                ],
                [
                    1176.9473684210525,
                    892.2807017543859
                ],
                [
                    1175.1929824561403,
                    1041.4035087719296
                ],
                [
                    1159.4035087719296,
                    1046.6666666666665
                ],
                [
                    1097.9999999999998,
                    995.7894736842104
                ],
                [
                    1106.7719298245613,
                    799.298245614035
                ],
                [
                    1076.9473684210525,
                    809.8245614035087
                ],
                [
                    1066.4210526315787,
                    809.8245614035087
                ],
                [
                    1055.8947368421052,
                    939.6491228070174
                ],
                [
                    829.5789473684209,
                    969.4736842105262
                ],
                [
                    806.7719298245613,
                    839.6491228070174
                ],
                [
                    773.4385964912279,
                    843.157894736842
                ],
                [
                    805.017543859649,
                    1050.1754385964912
                ],
                [
                    827.8245614035087,
                    1067.7192982456138
                ],
                [
                    855.8947368421052,
                    1183.5087719298244
                ],
                [
                    883.9649122807017,
                    1309.8245614035086
                ]
            ],
            "group_id": null,
            "shape_type": "polygon",
            "flags": {}
        },
        {
            "label": "chair",
            "points": [
                [
                    278.7017543859649,
                    890.5263157894735
                ],
                [
                    257.64912280701753,
                    929.1228070175437
                ],
                [
                    282.2105263157894,
                    1009.8245614035086
                ],
                [
                    333.0877192982456,
                    1146.6666666666665
                ],
                [
                    282.2105263157894,
                    1048.4210526315787
                ],
                [
                    238.35087719298244,
                    1067.7192982456138
                ],
                [
                    341.85964912280696,
                    1437.8947368421052
                ],
                [
                    355.0,
                    1459.0
                ],
                [
                    519.0,
                    1459.0
                ],
                [
                    690.9824561403508,
                    1385.2631578947367
                ],
                [
                    710.0,
                    1459.0
                ],
                [
                    768.1754385964912,
                    1458.9473684210525
                ],
                [
                    726.0701754385964,
                    953.6842105263156
                ],
                [
                    689.2280701754386,
                    936.1403508771928
                ],
                [
                    668.1754385964912,
                    829.1228070175438
                ],
                [
                    620.8070175438596,
                    837.8947368421052
                ],
                [
                    606.7719298245613,
                    950.1754385964912
                ],
                [
                    336.59649122807014,
                    990.5263157894735
                ],
                [
                    301.50877192982455,
                    885.2631578947368
                ]
            ],
            "group_id": null,
            "shape_type": "polygon",
            "flags": {}
        },
        {
            "label": "chair",
            "points": [
                [
                    331.3333333333333,
                    767.7192982456139
                ],
                [
                    299.7543859649123,
                    765.9649122807017
                ],
                [
                    329.57894736842104,
                    997.5438596491226
                ],
                [
                    610.2807017543859,
                    953.6842105263156
                ],
                [
                    638.3508771929824,
                    832.6315789473683
                ],
                [
                    634.8421052631578,
                    734.3859649122807
                ],
                [
                    594.4912280701753,
                    730.877192982456
                ],
                [
                    597.9999999999999,
                    811.5789473684209
                ],
                [
                    343.6140350877193,
                    829.1228070175438
                ],
                [
                    343.6140350877193,
                    783.5087719298244
                ]
            ],
            "group_id": null,
            "shape_type": "polygon",
            "flags": {}
        },
        {
            "label": "chair",
            "points": [
                [
                    297.99999999999994,
                    657.1929824561403
                ],
                [
                    276.9473684210526,
                    671.2280701754385
                ],
                [
                    294.4912280701754,
                    764.2105263157894
                ],
                [
                    294.4912280701754,
                    832.6315789473683
                ],
                [
                    268.1754385964912,
                    739.6491228070174
                ],
                [
                    234.84210526315786,
                    743.157894736842
                ],
                [
                    271.6842105263158,
                    897.5438596491227
                ],
                [
                    340.1052631578947,
                    965.9649122807016
                ],
                [
                    583.9649122807017,
                    920.3508771929824
                ],
                [
                    580.4561403508771,
                    639.6491228070174
                ],
                [
                    547.1228070175438,
                    643.157894736842
                ],
                [
                    503.26315789473676,
                    723.8596491228069
                ],
                [
                    334.84210526315786,
                    732.6315789473683
                ]
            ],
            "group_id": null,
            "shape_type": "polygon",
            "flags": {}
        },
        {
            "label": "chair",
            "points": [
                [
                    301.50877192982455,
                    576.4912280701753
                ],
                [
                    292.7368421052631,
                    579.9999999999999
                ],
                [
                    296.24561403508767,
                    643.157894736842
                ],
                [
                    273.43859649122805,
                    636.1403508771929
                ],
                [
                    273.43859649122805,
                    667.7192982456139
                ],
                [
                    285.719298245614,
                    722.1052631578947
                ],
                [
                    287.4736842105263,
                    660.7017543859648
                ],
                [
                    305.0175438596491,
                    650.1754385964912
                ],
                [
                    340.1052631578947,
                    734.3859649122807
                ],
                [
                    545.3684210526316,
                    704.5614035087718
                ],
                [
                    543.6140350877192,
                    609.8245614035087
                ],
                [
                    533.0877192982456,
                    565.9649122807017
                ],
                [
                    510.28070175438586,
                    560.7017543859648
                ],
                [
                    508.52631578947364,
                    629.1228070175438
                ],
                [
                    420.8070175438596,
                    632.6315789473683
                ],
                [
                    354.14035087719293,
                    641.4035087719298
                ],
                [
                    322.5614035087719,
                    641.4035087719298
                ]
            ],
            "group_id": null,
            "shape_type": "polygon",
            "flags": {}
        },
        {
            "label": "chair",
            "points": [
                [
                    1185.7192982456138,
                    1201.0526315789473
                ],
                [
                    1155.8947368421052,
                    916.8421052631577
                ],
                [
                    1183.9649122807016,
                    722.1052631578947
                ],
                [
                    1155.8947368421052,
                    713.3333333333333
                ],
                [
                    1134.8421052631577,
                    808.0701754385964
                ],
                [
                    1080.4561403508771,
                    792.2807017543859
                ],
                [
                    1099.7543859649122,
                    651.9298245614034
                ],
                [
                    1064.6666666666665,
                    658.9473684210526
                ],
                [
                    1047.1228070175437,
                    734.3859649122807
                ],
                [
                    908.5263157894735,
                    744.9122807017543
                ],
                [
                    855.8947368421052,
                    762.4561403508771
                ],
                [
                    836.5964912280701,
                    671.2280701754385
                ],
                [
                    817.298245614035,
                    676.4912280701753
                ],
                [
                    820.8070175438596,
                    799.298245614035
                ],
                [
                    845.3684210526314,
                    1004.5614035087717
                ],
                [
                    905.017543859649,
                    1108.0701754385964
                ],
                [
                    1122.5614035087717,
                    1048.4210526315787
                ],
                [
                    1138.3508771929824,
                    1176.4912280701753
                ]
            ],
            "group_id": null,
            "shape_type": "polygon",
            "flags": {}
        },
        {
            "label": "chair",
            "points": [
                [
                    741.8596491228069,
                    872.9824561403508
                ],
                [
                    659.4035087719298,
                    892.2807017543859
                ],
                [
                    738.3508771929824,
                    1137.8947368421052
                ],
                [
                    771.6842105263157,
                    1122.1052631578946
                ],
                [
                    780.4561403508771,
                    1236.1403508771928
                ],
                [
                    799.7543859649122,
                    1348.4210526315787
                ],
                [
                    797.9999999999999,
                    1406.315789473684
                ],
                [
                    884.0,
                    1459.0
                ],
                [
                    1126.0701754385964,
                    1429.1228070175437
                ],
                [
                    1129.578947368421,
                    1448.4210526315787
                ],
                [
                    1180.4561403508771,
                    1450.175438596491
                ],
                [
                    1178.7017543859647,
                    1336.1403508771928
                ],
                [
                    1199.7543859649122,
                    1295.7894736842104
                ],
                [
                    1148.877192982456,
                    1158.9473684210525
                ],
                [
                    1082.2105263157894,
                    1132.6315789473683
                ],
                [
                    859.4035087719298,
                    1150.1754385964912
                ],
                [
                    838.3508771929824,
                    1067.7192982456138
                ],
                [
                    833.0877192982455,
                    1055.438596491228
                ],
                [
                    754.1403508771929,
                    995.7894736842104
                ],
                [
                    743.6140350877192,
                    941.4035087719296
                ]
            ],
            "group_id": null,
            "shape_type": "polygon",
            "flags": {}
        },
        {
            "label": "chair",
            "points": [
                [
                    743.6140350877192,
                    718.5964912280701
                ],
                [
                    726.0701754385964,
                    736.1403508771929
                ],
                [
                    766.4210526315788,
                    860.7017543859648
                ],
                [
                    787.4736842105262,
                    920.3508771929824
                ],
                [
                    833.0877192982455,
                    1050.1754385964912
                ],
                [
                    861.157894736842,
                    1118.5964912280701
                ],
                [
                    941.8596491228069,
                    1127.3684210526314
                ],
                [
                    1112.0350877192982,
                    1097.5438596491226
                ],
                [
                    1119.0526315789473,
                    1146.6666666666665
                ],
                [
                    1166.4210526315787,
                    1102.8070175438595
                ],
                [
                    1141.8596491228068,
                    999.2982456140351
                ],
                [
                    1073.438596491228,
                    920.3508771929824
                ],
                [
                    1050.6315789473683,
                    909.8245614035086
                ],
                [
                    894.4912280701753,
                    930.8771929824561
                ],
                [
                    859.4035087719298,
                    876.4912280701753
                ],
                [
                    852.3859649122807,
                    839.6491228070174
                ],
                [
                    803.2631578947368,
                    801.0526315789473
                ],
                [
                    782.2105263157894,
                    748.4210526315788
                ],
                [
                    790.9824561403508,
                    722.1052631578947
                ],
                [
                    776.9473684210526,
                    716.8421052631578
                ]
            ],
            "group_id": null,
            "shape_type": "polygon",
            "flags": {}
        },
        {
            "label": "chair",
            "points": [
                [
                    133.0877192982456,
                    964.2105263157894
                ],
                [
                    55.89473684210526,
                    1083.5087719298244
                ],
                [
                    47.122807017543856,
                    1229.1228070175437
                ],
                [
                    206.77192982456137,
                    1365.9649122807016
                ],
                [
                    269.9298245614035,
                    1437.8947368421052
                ],
                [
                    289.0,
                    1459.0
                ],
                [
                    322.5614035087719,
                    1457.1929824561403
                ],
                [
                    283.9649122807017,
                    1315.0877192982455
                ],
                [
                    262.91228070175436,
                    1267.7192982456138
                ],
                [
                    285.719298245614,
                    1174.7368421052631
                ],
                [
                    245.36842105263156,
                    1006.3157894736842
                ],
                [
                    190.98245614035085,
                    948.4210526315787
                ]
            ],
            "group_id": null,
            "shape_type": "polygon",
            "flags": {}
        },
        {
            "label": "chair",
            "points": [
                [
                    206.77192982456137,
                    837.8947368421052
                ],
                [
                    143.6140350877193,
                    911.578947368421
                ],
                [
                    143.6140350877193,
                    965.9649122807016
                ],
                [
                    217.29824561403507,
                    962.4561403508771
                ],
                [
                    243.61403508771926,
                    1009.8245614035086
                ],
                [
                    262.91228070175436,
                    1030.877192982456
                ],
                [
                    287.4736842105263,
                    988.7719298245613
                ],
                [
                    259.4035087719298,
                    858.9473684210525
                ],
                [
                    259.4035087719298,
                    829.1228070175438
                ]
            ],
            "group_id": null,
            "shape_type": "polygon",
            "flags": {}
        },
        {
            "label": "chair",
            "points": [
                [
                    138.35087719298244,
                    772.9824561403508
                ],
                [
                    106.7719298245614,
                    820.3508771929824
                ],
                [
                    140.1052631578947,
                    839.6491228070174
                ],
                [
                    164.66666666666666,
                    872.9824561403508
                ],
                [
                    197.99999999999997,
                    858.9473684210525
                ],
                [
                    233.0877192982456,
                    841.4035087719298
                ],
                [
                    257.64912280701753,
                    820.3508771929824
                ],
                [
                    238.35087719298244,
                    729.1228070175438
                ],
                [
                    234.84210526315786,
                    711.5789473684209
                ],
                [
                    220.80701754385962,
                    697.5438596491227
                ],
                [
                    166.42105263157893,
                    713.3333333333333
                ]
            ],
            "group_id": null,
            "shape_type": "polygon",
            "flags": {}
        },
        {
            "label": "chair",
            "points": [
                [
                    169.92982456140348,
                    713.3333333333333
                ],
                [
                    162.91228070175436,
                    701.0526315789473
                ],
                [
                    203.26315789473682,
                    620.3508771929824
                ],
                [
                    259.4035087719298,
                    606.3157894736842
                ],
                [
                    266.4210526315789,
                    637.8947368421052
                ],
                [
                    282.2105263157894,
                    683.5087719298244
                ],
                [
                    282.2105263157894,
                    709.8245614035087
                ],
                [
                    278.7017543859649,
                    748.4210526315788
                ],
                [
                    254.14035087719293,
                    748.4210526315788
                ],
                [
                    243.61403508771926,
                    709.8245614035087
                ],
                [
                    229.57894736842104,
                    702.8070175438596
                ],
                [
                    227.82456140350874,
                    697.5438596491227
                ]
            ],
            "group_id": null,
            "shape_type": "polygon",
            "flags": {}
        },
        {
            "label": "chair",
            "points": [
                [
                    1212.0350877192982,
                    727.3684210526314
                ],
                [
                    1134.8421052631577,
                    676.4912280701753
                ],
                [
                    1103.2631578947367,
                    697.5438596491227
                ],
                [
                    1133.0877192982455,
                    771.2280701754385
                ],
                [
                    1152.3859649122805,
                    864.2105263157894
                ],
                [
                    1164.6666666666665,
                    937.8947368421052
                ],
                [
                    1243.6140350877192,
                    988.7719298245613
                ],
                [
                    1215.5438596491226,
                    1220.3508771929824
                ],
                [
                    1224.3157894736842,
                    1243.1578947368419
                ],
                [
                    1262.9122807017543,
                    1169.4736842105262
                ],
                [
                    1429.5789473684208,
                    1134.3859649122805
                ],
                [
                    1448.8771929824559,
                    1187.0175438596489
                ],
                [
                    1489.2280701754385,
                    953.6842105263156
                ],
                [
                    1447.1228070175437,
                    932.6315789473683
                ],
                [
                    1269.9298245614034,
                    972.9824561403507
                ],
                [
                    1262.9122807017543,
                    758.9473684210525
                ]
            ],
            "group_id": null,
            "shape_type": "polygon",
            "flags": {}
        }
    ],
    "imagePath": "../../RECommended_TIFF/196_IMG_0414.json",
    "imageData": null,
    "imageHeight": 1460,
    "imageWidth": 2193
}