{
    "version": "4.5.6",
    "flags": {},
    "shapes": [
        {
            "label": "cup",
            "points": [
                [
                    847.3809523809524,
                    827.6666666666666
                ],
                [
                    858.4920634920635,
                    1045.126984126984
                ],
                [
                    872.7777777777778,
                    1065.7619047619048
                ],
                [
                    915.6349206349206,
                    1073.6984126984128
                ],
                [
                    1026.7460317460318,
                    1072.111111111111
                ],
                [
                    1041.031746031746,
                    1064.1746031746031
                ],
                [
                    1055.3174603174602,
                    1038.7777777777778
                ],
                [
                    1058.4920634920634,
                    975.2857142857143
                ],
                [
                    1098.1746031746031,
                    938.7777777777777
                ],
                [
                    1112.4603174603174,
                    907.031746031746
                ],
                [
                    1077.5396825396826,
                    835.6031746031746
                ],
                [
                    1063.2539682539682,
                    834.015873015873
                ],
                [
                    1058.4920634920634,
                    818.1428571428571
                ],
                [
                    958.4920634920635,
                    808.6190476190476
                ],
                [
                    888.6507936507936,
                    814.968253968254
                ]
            ],
            "group_id": null,
            "shape_type": "polygon",
            "flags": {}
        },
        {
            "label": "cup",
            "points": [
                [
                    431.5079365079365,
                    803.8571428571429
                ],
                [
                    409.2857142857143,
                    916.5555555555555
                ],
                [
                    414.04761904761904,
                    989.5714285714287
                ],
                [
                    510.8730158730159,
                    1005.4444444444443
                ],
                [
                    607.6984126984127,
                    975.2857142857143
                ],
                [
                    596.5873015873016,
                    843.5396825396825
                ],
                [
                    575.952380952381,
                    803.8571428571429
                ],
                [
                    496.58730158730157,
                    797.5079365079365
                ]
            ],
            "group_id": null,
            "shape_type": "polygon",
            "flags": {}
        },
        {
            "label": "cup",
            "points": [
                [
                    591.8253968253969,
                    811.7936507936508
                ],
                [
                    588.6507936507936,
                    827.6666666666666
                ],
                [
                    604.5238095238095,
                    973.6984126984127
                ],
                [
                    656.9047619047619,
                    975.2857142857143
                ],
                [
                    729.9206349206349,
                    967.3492063492064
                ],
                [
                    721.984126984127,
                    919.7301587301587
                ],
                [
                    726.7460317460317,
                    870.5238095238095
                ],
                [
                    726.7460317460317,
                    808.6190476190476
                ],
                [
                    633.0952380952381,
                    807.031746031746
                ]
            ],
            "group_id": null,
            "shape_type": "polygon",
            "flags": {}
        },
        {
            "label": "cup",
            "points": [
                [
                    756.9047619047619,
                    808.6190476190476
                ],
                [
                    760.0793650793651,
                    861.0
                ],
                [
                    709.2857142857143,
                    887.984126984127
                ],
                [
                    715.6349206349206,
                    932.4285714285714
                ],
                [
                    737.8571428571429,
                    973.6984126984127
                ],
                [
                    758.4920634920635,
                    975.2857142857143
                ],
                [
                    766.4285714285714,
                    994.3333333333333
                ],
                [
                    850.5555555555555,
                    995.9206349206349
                ],
                [
                    848.968253968254,
                    824.4920634920635
                ],
                [
                    890.2380952380952,
                    811.7936507936508
                ],
                [
                    907.6984126984127,
                    811.7936507936508
                ],
                [
                    907.6984126984127,
                    800.6825396825396
                ],
                [
                    788.6507936507936,
                    797.5079365079365
                ]
            ],
            "group_id": null,
            "shape_type": "polygon",
            "flags": {}
        },
        {
            "label": "cup",
            "points": [
                [
                    599.7619047619047,
                    110.20634920634922
                ],
                [
                    607.6984126984127,
                    218.14285714285717
                ],
                [
                    785.4761904761905,
                    216.55555555555554
                ],
                [
                    782.3015873015873,
                    130.84126984126985
                ],
                [
                    698.1746031746031,
                    94.33333333333334
                ],
                [
                    625.1587301587301,
                    94.33333333333334
                ]
            ],
            "group_id": null,
            "shape_type": "polygon",
            "flags": {}
        },
        {
            "label": "cup",
            "points": [
                [
                    780.7142857142857,
                    137.19047619047618
                ],
                [
                    742.6190476190476,
                    153.06349206349205
                ],
                [
                    725.1587301587301,
                    214.96825396825398
                ],
                [
                    948.968253968254,
                    216.55555555555554
                ],
                [
                    942.6190476190476,
                    143.53968253968253
                ],
                [
                    855.3174603174604,
                    118.14285714285714
                ],
                [
                    812.4603174603175,
                    126.07936507936509
                ]
            ],
            "group_id": null,
            "shape_type": "polygon",
            "flags": {}
        },
        {
            "label": "cup",
            "points": [
                [
                    1045.7936507936508,
                    148.3015873015873
                ],
                [
                    1052.142857142857,
                    218.14285714285717
                ],
                [
                    1269.6031746031747,
                    218.14285714285717
                ],
                [
                    1271.1904761904761,
                    197.5079365079365
                ],
                [
                    1247.3809523809523,
                    172.11111111111111
                ],
                [
                    1207.6984126984128,
                    176.87301587301587
                ],
                [
                    1199.7619047619048,
                    180.04761904761904
                ],
                [
                    1193.4126984126983,
                    138.77777777777777
                ],
                [
                    1147.3809523809523,
                    122.9047619047619
                ],
                [
                    1098.1746031746031,
                    122.9047619047619
                ],
                [
                    1071.1904761904761,
                    130.84126984126985
                ]
            ],
            "group_id": null,
            "shape_type": "polygon",
            "flags": {}
        },
        {
            "label": "cup",
            "points": [
                [
                    1814.047619047619,
                    127.66666666666666
                ],
                [
                    1825.1587301587301,
                    227.66666666666669
                ],
                [
                    1995.0,
                    232.42857142857144
                ],
                [
                    1991.8253968253969,
                    102.26984126984127
                ],
                [
                    1925.1587301587301,
                    87.98412698412699
                ],
                [
                    1872.7777777777778,
                    100.68253968253967
                ],
                [
                    1847.3809523809523,
                    107.03174603174602
                ]
            ],
            "group_id": null,
            "shape_type": "polygon",
            "flags": {}
        },
        {
            "label": "cup",
            "points": [
                [
                    428.3333333333333,
                    22.904761904761905
                ],
                [
                    444.2063492063492,
                    45.12698412698413
                ],
                [
                    417.22222222222223,
                    62.58730158730158
                ],
                [
                    418.8095238095238,
                    226.07936507936506
                ],
                [
                    593.4126984126984,
                    221.3174603174603
                ],
                [
                    599.7619047619047,
                    87.98412698412699
                ],
                [
                    596.5873015873016,
                    61.0
                ],
                [
                    607.6984126984127,
                    49.888888888888886
                ],
                [
                    561.6666666666666,
                    7.031746031746032
                ],
                [
                    531.5079365079365,
                    3.857142857142854
                ],
                [
                    434.6825396825397,
                    3.857142857142854
                ]
            ],
            "group_id": null,
            "shape_type": "polygon",
            "flags": {}
        }
    ],
    "imagePath": "../../RECommended_TIFF/401_IMG_0637.json",
    "imageData": null,
    "imageHeight": 1460,
    "imageWidth": 2193
}